{
  "project_info": {
    "project_number": "800573400072",
    "project_id": "hi-texi",
    "storage_bucket": "hi-texi.appspot.com"
  },
  "client": [
    {
      "client_info": {
        "mobilesdk_app_id": "1:800573400072:android:f25a06e631925ec321ddbd",
        "android_client_info": {
          "package_name": "com.mukeshdev.hitexi"
        }
      },
      "oauth_client": [
        {
          "client_id": "800573400072-1npg1smrbb78c1q6ilihg8fo3lngvepf.apps.googleusercontent.com",
          "client_type": 3
        }
      ],
      "api_key": [
        {
          "current_key": "AIzaSyBemkacu0LBhlpsZx6avpMdfjAkktuGs7k"
        }
      ],
      "services": {
        "appinvite_service": {
          "other_platform_oauth_client": [
            {
              "client_id": "800573400072-1npg1smrbb78c1q6ilihg8fo3lngvepf.apps.googleusercontent.com",
              "client_type": 3
            }
          ]
        }
      }
    }
  ],
  "configuration_version": "1"
}